cfx_account/__init__.py
cfx_account/account.py
cfx_account/messages.py
cfx_account/py.typed
cfx_account/types.py
cfx_account/_utils/__init__.py
cfx_account/_utils/signing.py
cfx_account/_utils/transactions.py
cfx_account/_utils/structured_data/__init__.py
cfx_account/_utils/structured_data/eth_account_legacy_hashing.py
cfx_account/_utils/structured_data/eth_account_legacy_validation.py
cfx_account/_utils/structured_data/hashing.py
cfx_account/_utils/structured_data/validation.py
cfx_account/_utils/transactions/__init__.py
cfx_account/_utils/transactions/base.py
cfx_account/_utils/transactions/cip1559_transactions.py
cfx_account/_utils/transactions/legacy_transactions.py
cfx_account/_utils/transactions/transaction_utils.py
cfx_account/_utils/transactions/transactions.py
cfx_account/signers/__init__.py
cfx_account/signers/local.py
cfx_account/transactions/__init__.py
cfx_account/transactions/base.py
cfx_account/transactions/cip1559_transactions.py
cfx_account/transactions/legacy_transactions.py
cfx_account/transactions/transaction_utils.py
cfx_account/transactions/transactions.py
tests/__init__.py
tests/account_test.py
tests/cip1559_transaction_test.py
tests/encryption_test.py
tests/mnemonic_test.py
tests/sign_test.py
tests/test_utils.py
cfx_account-1.2.2.dist-info/METADATA
cfx_account-1.2.2.dist-info/WHEEL
cfx_account-1.2.2.dist-info/top_level.txt
cfx_account-1.2.2.dist-info/RECORD
