Metadata-Version: 2.1
Name: cfx-account
Version: 1.2.2
Summary: Conflux account
Author: The conflux foundation
Author-email: wangpan@conflux-chain.org
Keywords: blockchain,conflux,sign
Classifier: Development Status :: 3 - Alpha
Classifier: Intended Audience :: Education
Classifier: Programming Language :: Python :: 2
Classifier: Programming Language :: Python :: 3
Classifier: Operating System :: MacOS :: MacOS X
Classifier: Operating System :: Microsoft :: Windows
Requires-Dist: eth-account>=0.13.1
Requires-Dist: cfx-address>=1.2.0
Requires-Dist: cfx-utils>=1.0.5
Provides-Extra: dev
Requires-Dist: pytest<9,>8; extra == "dev"
Requires-Dist: wheel; extra == "dev"
Provides-Extra: docs
Provides-Extra: linter
Provides-Extra: tester
Requires-Dist: pytest<9,>8; extra == "tester"
